[
    {
        "userId": "143373549338361856",
        "name": "saltenator",
        "tradelink": "https://steamcommunity.com/tradeoffer/new/?partner=325176772&token=DmiLKZ6K",
        "interests": [
            "banana",
            "banana",
            "banana"
        ],
        "steamID64": "76561198285442500"
    },
    {
        "userId": "224233557927657472",
        "name": "heepings",
        "tradelink": "https://steamcommunity.com/tradeoffer/new/?partner=361284731&token=4tdbsf9f",
        "interests": [
            "cock",
            "ball",
            "torture"
        ],
        "steamID64": "76561198321550459"
    }
]